simplex/__init__.py
simplex/_http_client.py
simplex/client.py
simplex/errors.py
simplex/types.py
simplex-2.0.4.dist-info/licenses/LICENSE
simplex-2.0.4.dist-info/METADATA
simplex-2.0.4.dist-info/WHEEL
simplex-2.0.4.dist-info/top_level.txt
simplex-2.0.4.dist-info/RECORD
