Metadata-Version: 2.4
Name: simplex
Version: 2.0.4
Summary: Official Python SDK for the Simplex API
Author-email: Simplex <support@simplex.sh>
License: MIT
Project-URL: Homepage, https://simplex.sh
Project-URL: Documentation, https://docs.simplex.sh
Project-URL: Repository, https://github.com/simplexlabs/simplex-python
Keywords: simplex,api,sdk,workflow,automation,browser,scraping
Classifier: Development Status :: 5 - Production/Stable
Classifier: Intended Audience :: Developers
Classifier: Topic :: Software Development :: Libraries :: Python Modules
Classifier: License :: OSI Approved :: MIT License
Classifier: Programming Language :: Python :: 3
Classifier: Programming Language :: Python :: 3.9
Classifier: Programming Language :: Python :: 3.10
Classifier: Programming Language :: Python :: 3.11
Classifier: Programming Language :: Python :: 3.12
Classifier: Programming Language :: Python :: 3.13
Classifier: Operating System :: OS Independent
Requires-Python: >=3.9
License-File: LICENSE
Requires-Dist: requests>=2.25.0
Provides-Extra: dev
Requires-Dist: pytest>=7.0.0; extra == "dev"
Requires-Dist: mypy>=1.0.0; extra == "dev"
Requires-Dist: types-requests>=2.25.0; extra == "dev"
Dynamic: license-file
